{
  "interface": "manage/user",
  "note": "管理新闻",
  "get": [
    {
      "code": 200,
      "message": "成功获得用户新闻列表",
      "data": [
        {
          "userId": "用户id",
          "userName": "用户姓名",
          "logoUrl":"头像地址"
        }
      ]
    },
    {
      "code": 500,
      "message": "权限不足",
      "data": {}
    }
  ],
  "put": [
    {
      "code": 200,
      "message": "修改成功",
      "data": {
      }
    },
    {
      "code": 500,
      "message": "权限不足",
      "data": {}
    }
  ]
}